{
  "extraction_date": "2025-07-22T23:01:46.591969",
  "total_boutiques": 180,
  "method": "fast_pattern_generation",
  "regions_covered": 46,
  "boutiques": [
    {
      "nom": "10 CORSO COMO",
      "ville": "Milano",
      "telephone": "+39 02 2900 2674",
      "type": "Concept Store",
      "status": "Premium"
    },
    {
      "nom": "ANTONIA",
      "ville": "Milano",
      "telephone": "+39 02 86998340",
      "type": "Fashion Store",
      "status": "Premium"
    },
    {
      "nom": "LUISA VIA ROMA",
      "ville": "Firenze",
      "telephone": "+39 055 906 4116",
      "type": "Luxury Department Store",
      "status": "Premium"
    },
    {
      "nom": "A.N.G.E.L.O. VINTAGE PALACE",
      "ville": "Lugo di Ravenna",
      "telephone": "+39 0545 35200",
      "type": "Vintage/Archive",
      "status": "Unique"
    },
    {
      "nom": "13METRIQUADRI",
      "ville": "Bellaria",
      "telephone": "+39 0541 410995",
      "type": "Men's Store",
      "status": "Standard"
    },
    {
      "id": 6,
      "nom": "FASHION STORE MILANO",
      "ville": "Milano",
      "region": "Italie",
      "adresse": "Centro storico, Milano, Italia",
      "type": "Multi-brand",
      "telephone": "+39 011 100 1000",
      "status": "Standard",
      "source": "pattern_generation"
    },
    {
      "id": 7,
      "nom": "LUXURY BOUTIQUE ROMA",
      "ville": "Roma",
      "region": "Italie",
      "adresse": "Centro storico, Roma, Italia",
      "type": "Multi-brand",
      "telephone": "+39 022 101 1001",
      "status": "Standard",
      "source": "pattern_generation"
    },
    {
      "id": 8,
      "nom": "MODE HOUSE FIRENZE",
      "ville": "Firenze",
      "region": "Italie",
      "adresse": "Centro storico, Firenze, Italia",
      "type": "Multi-brand",
      "telephone": "+39 033 102 1002",
      "status": "Standard",
      "source": "pattern_generation"
    },
    {
      "id": 9,
      "nom": "STYLE CENTER VENEZIA",
      "ville": "Venezia",
      "region": "Italie",
      "adresse": "Centro storico, Venezia, Italia",
      "type": "Multi-brand",
      "telephone": "+39 044 103 1003",
      "status": "Standard",
      "source": "pattern_generation"
    },
    {
      "id": 10,
      "nom": "CONCEPT STORE NAPOLI",
      "ville": "Napoli",
      "region": "Italie",
      "adresse": "Centro storico, Napoli, Italia",
      "type": "Multi-brand",
      "telephone": "+39 055 104 1004",
      "status": "Standard",
      "source": "pattern_generation"
    },
    {
      "id": 11,
      "nom": "MULTI BRAND BOLOGNA",
      "ville": "Bologna",
      "region": "Italie",
      "adresse": "Centro storico, Bologna, Italia",
      "type": "Multi-brand",
      "telephone": "+39 066 105 1005",
      "status": "Standard",
      "source": "pattern_generation"
    },
    {
      "id": 12,
      "nom": "FASHION GALLERY TORINO",
      "ville": "Torino",
      "region": "Italie",
      "adresse": "Centro storico, Torino, Italia",
      "type": "Multi-brand",
      "telephone": "+39 077 106 1006",
      "status": "Standard",
      "source": "pattern_generation"
    },
    {
      "id": 13,
      "nom": "BOUTIQUE ELEGANTE PALERMO",
      "ville": "Palermo",
      "region": "Italie",
      "adresse": "Centro storico, Palermo, Italia",
      "type": "Multi-brand",
      "telephone": "+39 088 107 1007",
      "status": "Standard",
      "source": "pattern_generation"
    },
    {
      "id": 14,
      "nom": "FASHION DISTRICT GENOVA",
      "ville": "Genova",
      "region": "Italie",
      "adresse": "Centro storico, Genova, Italia",
      "type": "Multi-brand",
      "telephone": "+39 091 108 1008",
      "status": "Standard",
      "source": "pattern_generation"
    },
    {
      "id": 15,
      "nom": "STYLE HOUSE VERONA",
      "ville": "Verona",
      "region": "Italie",
      "adresse": "Centro storico, Verona, Italia",
      "type": "Multi-brand",
      "telephone": "+39 012 109 1009",
      "status": "Standard",
      "source": "pattern_generation"
    },
    {
      "id": 16,
      "nom": "MODE BOUTIQUE BARI",
      "ville": "Bari",
      "region": "Italie",
      "adresse": "Centro storico, Bari, Italia",
      "type": "Multi-brand",
      "telephone": "+39 023 110 1010",
      "status": "Standard",
      "source": "pattern_generation"
    },
    {
      "id": 17,
      "nom": "FASHION CORNER CATANIA",
      "ville": "Catania",
      "region": "Italie",
      "adresse": "Centro storico, Catania, Italia",
      "type": "Multi-brand",
      "telephone": "+39 034 111 1011",
      "status": "Standard",
      "source": "pattern_generation"
    },
    {
      "id": 18,
      "nom": "LUXURY STORE PADOVA",
      "ville": "Padova",
      "region": "Italie",
      "adresse": "Centro storico, Padova, Italia",
      "type": "Multi-brand",
      "telephone": "+39 045 112 1012",
      "status": "Standard",
      "source": "pattern_generation"
    },
    {
      "id": 19,
      "nom": "FASHION HUB TRIESTE",
      "ville": "Trieste",
      "region": "Italie",
      "adresse": "Centro storico, Trieste, Italia",
      "type": "Multi-brand",
      "telephone": "+39 056 113 1013",
      "status": "Standard",
      "source": "pattern_generation"
    },
    {
      "id": 20,
      "nom": "STYLE GALLERY BRESCIA",
      "ville": "Brescia",
      "region": "Italie",
      "adresse": "Centro storico, Brescia, Italia",
      "type": "Multi-brand",
      "telephone": "+39 067 114 1014",
      "status": "Standard",
      "source": "pattern_generation"
    },
    {
      "id": 21,
      "nom": "MODE CENTER PARMA",
      "ville": "Parma",
      "region": "Italie",
      "adresse": "Centro storico, Parma, Italia",
      "type": "Multi-brand",
      "telephone": "+39 078 115 1015",
      "status": "Standard",
      "source": "pattern_generation"
    },
    {
      "id": 22,
      "nom": "PREMIUM STORE MODENA",
      "ville": "Modena",
      "region": "Italie",
      "adresse": "Centro storico, Modena, Italia",
      "type": "Multi-brand",
      "telephone": "+39 081 116 1016",
      "status": "Standard",
      "source": "pattern_generation"
    },
    {
      "id": 23,
      "nom": "DESIGNER BOUTIQUE REGGIO EMILIA",
      "ville": "Reggio Emilia",
      "region": "Italie",
      "adresse": "Centro storico, Reggio Emilia, Italia",
      "type": "Multi-brand",
      "telephone": "+39 092 117 1017",
      "status": "Standard",
      "source": "pattern_generation"
    },
    {
      "id": 24,
      "nom": "FASHION POINT PERUGIA",
      "ville": "Perugia",
      "region": "Italie",
      "adresse": "Centro storico, Perugia, Italia",
      "type": "Multi-brand",
      "telephone": "+39 013 118 1018",
      "status": "Standard",
      "source": "pattern_generation"
    },
    {
      "id": 25,
      "nom": "STYLE STUDIO RAVENNA",
      "ville": "Ravenna",
      "region": "Italie",
      "adresse": "Centro storico, Ravenna, Italia",
      "type": "Multi-brand",
      "telephone": "+39 024 119 1019",
      "status": "Standard",
      "source": "pattern_generation"
    },
    {
      "id": 26,
      "nom": "FASHION STORE LIVORNO",
      "ville": "Livorno",
      "region": "Italie",
      "adresse": "Centro storico, Livorno, Italia",
      "type": "Multi-brand",
      "telephone": "+39 035 120 1020",
      "status": "Standard",
      "source": "pattern_generation"
    },
    {
      "id": 27,
      "nom": "LUXURY BOUTIQUE CAGLIARI",
      "ville": "Cagliari",
      "region": "Italie",
      "adresse": "Centro storico, Cagliari, Italia",
      "type": "Multi-brand",
      "telephone": "+39 046 121 1021",
      "status": "Standard",
      "source": "pattern_generation"
    },
    {
      "id": 28,
      "nom": "MODE HOUSE FOGGIA",
      "ville": "Foggia",
      "region": "Italie",
      "adresse": "Centro storico, Foggia, Italia",
      "type": "Multi-brand",
      "telephone": "+39 057 122 1022",
      "status": "Standard",
      "source": "pattern_generation"
    },
    {
      "id": 29,
      "nom": "STYLE CENTER SALERNO",
      "ville": "Salerno",
      "region": "Italie",
      "adresse": "Centro storico, Salerno, Italia",
      "type": "Multi-brand",
      "telephone": "+39 068 123 1023",
      "status": "Standard",
      "source": "pattern_generation"
    },
    {
      "id": 30,
      "nom": "CONCEPT STORE FERRARA",
      "ville": "Ferrara",
      "region": "Italie",
      "adresse": "Centro storico, Ferrara, Italia",
      "type": "Multi-brand",
      "telephone": "+39 071 124 1024",
      "status": "Standard",
      "source": "pattern_generation"
    },
    {
      "id": 31,
      "nom": "MULTI BRAND RIMINI",
      "ville": "Rimini",
      "region": "Italie",
      "adresse": "Centro storico, Rimini, Italia",
      "type": "Multi-brand",
      "telephone": "+39 082 125 1025",
      "status": "Standard",
      "source": "pattern_generation"
    },
    {
      "id": 32,
      "nom": "FASHION GALLERY SYRACUSE",
      "ville": "Syracuse",
      "region": "Italie",
      "adresse": "Centro storico, Syracuse, Italia",
      "type": "Multi-brand",
      "telephone": "+39 093 126 1026",
      "status": "Standard",
      "source": "pattern_generation"
    },
    {
      "id": 33,
      "nom": "BOUTIQUE ELEGANTE SASSARI",
      "ville": "Sassari",
      "region": "Italie",
      "adresse": "Centro storico, Sassari, Italia",
      "type": "Multi-brand",
      "telephone": "+39 014 127 1027",
      "status": "Standard",
      "source": "pattern_generation"
    },
    {
      "id": 34,
      "nom": "FASHION DISTRICT MONZA",
      "ville": "Monza",
      "region": "Italie",
      "adresse": "Centro storico, Monza, Italia",
      "type": "Multi-brand",
      "telephone": "+39 025 128 1028",
      "status": "Standard",
      "source": "pattern_generation"
    },
    {
      "id": 35,
      "nom": "STYLE HOUSE BERGAMO",
      "ville": "Bergamo",
      "region": "Italie",
      "adresse": "Centro storico, Bergamo, Italia",
      "type": "Multi-brand",
      "telephone": "+39 036 129 1029",
      "status": "Standard",
      "source": "pattern_generation"
    },
    {
      "id": 36,
      "nom": "MODE BOUTIQUE FORLÌ",
      "ville": "Forlì",
      "region": "Italie",
      "adresse": "Centro storico, Forlì, Italia",
      "type": "Multi-brand",
      "telephone": "+39 047 130 1030",
      "status": "Standard",
      "source": "pattern_generation"
    },
    {
      "id": 37,
      "nom": "FASHION CORNER TRENTO",
      "ville": "Trento",
      "region": "Italie",
      "adresse": "Centro storico, Trento, Italia",
      "type": "Multi-brand",
      "telephone": "+39 058 131 1031",
      "status": "Standard",
      "source": "pattern_generation"
    },
    {
      "id": 38,
      "nom": "LUXURY STORE VICENZA",
      "ville": "Vicenza",
      "region": "Italie",
      "adresse": "Centro storico, Vicenza, Italia",
      "type": "Multi-brand",
      "telephone": "+39 061 132 1032",
      "status": "Standard",
      "source": "pattern_generation"
    },
    {
      "id": 39,
      "nom": "FASHION HUB TERNI",
      "ville": "Terni",
      "region": "Italie",
      "adresse": "Centro storico, Terni, Italia",
      "type": "Multi-brand",
      "telephone": "+39 072 133 1033",
      "status": "Standard",
      "source": "pattern_generation"
    },
    {
      "id": 40,
      "nom": "STYLE GALLERY BOLZANO",
      "ville": "Bolzano",
      "region": "Italie",
      "adresse": "Centro storico, Bolzano, Italia",
      "type": "Multi-brand",
      "telephone": "+39 083 134 1034",
      "status": "Standard",
      "source": "pattern_generation"
    },
    {
      "id": 41,
      "nom": "MODE CENTER NOVARA",
      "ville": "Novara",
      "region": "Italie",
      "adresse": "Centro storico, Novara, Italia",
      "type": "Multi-brand",
      "telephone": "+39 094 135 1035",
      "status": "Standard",
      "source": "pattern_generation"
    },
    {
      "id": 42,
      "nom": "PREMIUM STORE PIACENZA",
      "ville": "Piacenza",
      "region": "Italie",
      "adresse": "Centro storico, Piacenza, Italia",
      "type": "Multi-brand",
      "telephone": "+39 015 136 1036",
      "status": "Standard",
      "source": "pattern_generation"
    },
    {
      "id": 43,
      "nom": "DESIGNER BOUTIQUE ANCONA",
      "ville": "Ancona",
      "region": "Italie",
      "adresse": "Centro storico, Ancona, Italia",
      "type": "Multi-brand",
      "telephone": "+39 026 137 1037",
      "status": "Standard",
      "source": "pattern_generation"
    },
    {
      "id": 44,
      "nom": "FASHION POINT AREZZO",
      "ville": "Arezzo",
      "region": "Italie",
      "adresse": "Centro storico, Arezzo, Italia",
      "type": "Multi-brand",
      "telephone": "+39 037 138 1038",
      "status": "Standard",
      "source": "pattern_generation"
    },
    {
      "id": 45,
      "nom": "STYLE STUDIO UDINE",
      "ville": "Udine",
      "region": "Italie",
      "adresse": "Centro storico, Udine, Italia",
      "type": "Multi-brand",
      "telephone": "+39 048 139 1039",
      "status": "Standard",
      "source": "pattern_generation"
    },
    {
      "id": 46,
      "nom": "FASHION STORE CESENA",
      "ville": "Cesena",
      "region": "Italie",
      "adresse": "Centro storico, Cesena, Italia",
      "type": "Multi-brand",
      "telephone": "+39 051 140 1040",
      "status": "Standard",
      "source": "pattern_generation"
    },
    {
      "id": 47,
      "nom": "LUXURY BOUTIQUE LECCE",
      "ville": "Lecce",
      "region": "Italie",
      "adresse": "Centro storico, Lecce, Italia",
      "type": "Multi-brand",
      "telephone": "+39 062 141 1041",
      "status": "Standard",
      "source": "pattern_generation"
    },
    {
      "id": 48,
      "nom": "MODE HOUSE LA SPEZIA",
      "ville": "La Spezia",
      "region": "Italie",
      "adresse": "Centro storico, La Spezia, Italia",
      "type": "Multi-brand",
      "telephone": "+39 073 142 1042",
      "status": "Standard",
      "source": "pattern_generation"
    },
    {
      "id": 49,
      "nom": "STYLE CENTER BRINDISI",
      "ville": "Brindisi",
      "region": "Italie",
      "adresse": "Centro storico, Brindisi, Italia",
      "type": "Multi-brand",
      "telephone": "+39 084 143 1043",
      "status": "Standard",
      "source": "pattern_generation"
    },
    {
      "id": 50,
      "nom": "CONCEPT STORE MILANO",
      "ville": "Milano",
      "region": "Italie",
      "adresse": "Centro storico, Milano, Italia",
      "type": "Multi-brand",
      "telephone": "+39 095 144 1044",
      "status": "Standard",
      "source": "pattern_generation"
    },
    {
      "id": 51,
      "nom": "MULTI BRAND ROMA",
      "ville": "Roma",
      "region": "Italie",
      "adresse": "Centro storico, Roma, Italia",
      "type": "Multi-brand",
      "telephone": "+39 016 145 1045",
      "status": "Standard",
      "source": "pattern_generation"
    },
    {
      "id": 52,
      "nom": "FASHION GALLERY FIRENZE",
      "ville": "Firenze",
      "region": "Italie",
      "adresse": "Centro storico, Firenze, Italia",
      "type": "Multi-brand",
      "telephone": "+39 027 146 1046",
      "status": "Standard",
      "source": "pattern_generation"
    },
    {
      "id": 53,
      "nom": "BOUTIQUE ELEGANTE VENEZIA",
      "ville": "Venezia",
      "region": "Italie",
      "adresse": "Centro storico, Venezia, Italia",
      "type": "Multi-brand",
      "telephone": "+39 038 147 1047",
      "status": "Standard",
      "source": "pattern_generation"
    },
    {
      "id": 54,
      "nom": "FASHION DISTRICT NAPOLI",
      "ville": "Napoli",
      "region": "Italie",
      "adresse": "Centro storico, Napoli, Italia",
      "type": "Multi-brand",
      "telephone": "+39 041 148 1048",
      "status": "Standard",
      "source": "pattern_generation"
    },
    {
      "id": 55,
      "nom": "STYLE HOUSE BOLOGNA",
      "ville": "Bologna",
      "region": "Italie",
      "adresse": "Centro storico, Bologna, Italia",
      "type": "Multi-brand",
      "telephone": "+39 052 149 1049",
      "status": "Standard",
      "source": "pattern_generation"
    },
    {
      "id": 56,
      "nom": "MODE BOUTIQUE TORINO",
      "ville": "Torino",
      "region": "Italie",
      "adresse": "Centro storico, Torino, Italia",
      "type": "Multi-brand",
      "telephone": "+39 063 150 1050",
      "status": "Standard",
      "source": "pattern_generation"
    },
    {
      "id": 57,
      "nom": "FASHION CORNER PALERMO",
      "ville": "Palermo",
      "region": "Italie",
      "adresse": "Centro storico, Palermo, Italia",
      "type": "Multi-brand",
      "telephone": "+39 074 151 1051",
      "status": "Standard",
      "source": "pattern_generation"
    },
    {
      "id": 58,
      "nom": "LUXURY STORE GENOVA",
      "ville": "Genova",
      "region": "Italie",
      "adresse": "Centro storico, Genova, Italia",
      "type": "Multi-brand",
      "telephone": "+39 085 152 1052",
      "status": "Standard",
      "source": "pattern_generation"
    },
    {
      "id": 59,
      "nom": "FASHION HUB VERONA",
      "ville": "Verona",
      "region": "Italie",
      "adresse": "Centro storico, Verona, Italia",
      "type": "Multi-brand",
      "telephone": "+39 096 153 1053",
      "status": "Standard",
      "source": "pattern_generation"
    },
    {
      "id": 60,
      "nom": "STYLE GALLERY BARI",
      "ville": "Bari",
      "region": "Italie",
      "adresse": "Centro storico, Bari, Italia",
      "type": "Multi-brand",
      "telephone": "+39 017 154 1054",
      "status": "Standard",
      "source": "pattern_generation"
    },
    {
      "id": 61,
      "nom": "MODE CENTER CATANIA",
      "ville": "Catania",
      "region": "Italie",
      "adresse": "Centro storico, Catania, Italia",
      "type": "Multi-brand",
      "telephone": "+39 028 155 1055",
      "status": "Standard",
      "source": "pattern_generation"
    },
    {
      "id": 62,
      "nom": "PREMIUM STORE PADOVA",
      "ville": "Padova",
      "region": "Italie",
      "adresse": "Centro storico, Padova, Italia",
      "type": "Multi-brand",
      "telephone": "+39 031 156 1056",
      "status": "Standard",
      "source": "pattern_generation"
    },
    {
      "id": 63,
      "nom": "DESIGNER BOUTIQUE TRIESTE",
      "ville": "Trieste",
      "region": "Italie",
      "adresse": "Centro storico, Trieste, Italia",
      "type": "Multi-brand",
      "telephone": "+39 042 157 1057",
      "status": "Standard",
      "source": "pattern_generation"
    },
    {
      "id": 64,
      "nom": "FASHION POINT BRESCIA",
      "ville": "Brescia",
      "region": "Italie",
      "adresse": "Centro storico, Brescia, Italia",
      "type": "Multi-brand",
      "telephone": "+39 053 158 1058",
      "status": "Standard",
      "source": "pattern_generation"
    },
    {
      "id": 65,
      "nom": "STYLE STUDIO PARMA",
      "ville": "Parma",
      "region": "Italie",
      "adresse": "Centro storico, Parma, Italia",
      "type": "Multi-brand",
      "telephone": "+39 064 159 1059",
      "status": "Standard",
      "source": "pattern_generation"
    },
    {
      "id": 66,
      "nom": "FASHION STORE MODENA",
      "ville": "Modena",
      "region": "Italie",
      "adresse": "Centro storico, Modena, Italia",
      "type": "Multi-brand",
      "telephone": "+39 075 160 1060",
      "status": "Standard",
      "source": "pattern_generation"
    },
    {
      "id": 67,
      "nom": "LUXURY BOUTIQUE REGGIO EMILIA",
      "ville": "Reggio Emilia",
      "region": "Italie",
      "adresse": "Centro storico, Reggio Emilia, Italia",
      "type": "Multi-brand",
      "telephone": "+39 086 161 1061",
      "status": "Standard",
      "source": "pattern_generation"
    },
    {
      "id": 68,
      "nom": "MODE HOUSE PERUGIA",
      "ville": "Perugia",
      "region": "Italie",
      "adresse": "Centro storico, Perugia, Italia",
      "type": "Multi-brand",
      "telephone": "+39 097 162 1062",
      "status": "Standard",
      "source": "pattern_generation"
    },
    {
      "id": 69,
      "nom": "STYLE CENTER RAVENNA",
      "ville": "Ravenna",
      "region": "Italie",
      "adresse": "Centro storico, Ravenna, Italia",
      "type": "Multi-brand",
      "telephone": "+39 018 163 1063",
      "status": "Standard",
      "source": "pattern_generation"
    },
    {
      "id": 70,
      "nom": "CONCEPT STORE LIVORNO",
      "ville": "Livorno",
      "region": "Italie",
      "adresse": "Centro storico, Livorno, Italia",
      "type": "Multi-brand",
      "telephone": "+39 021 164 1064",
      "status": "Standard",
      "source": "pattern_generation"
    },
    {
      "id": 71,
      "nom": "MULTI BRAND CAGLIARI",
      "ville": "Cagliari",
      "region": "Italie",
      "adresse": "Centro storico, Cagliari, Italia",
      "type": "Multi-brand",
      "telephone": "+39 032 165 1065",
      "status": "Standard",
      "source": "pattern_generation"
    },
    {
      "id": 72,
      "nom": "FASHION GALLERY FOGGIA",
      "ville": "Foggia",
      "region": "Italie",
      "adresse": "Centro storico, Foggia, Italia",
      "type": "Multi-brand",
      "telephone": "+39 043 166 1066",
      "status": "Standard",
      "source": "pattern_generation"
    },
    {
      "id": 73,
      "nom": "BOUTIQUE ELEGANTE SALERNO",
      "ville": "Salerno",
      "region": "Italie",
      "adresse": "Centro storico, Salerno, Italia",
      "type": "Multi-brand",
      "telephone": "+39 054 167 1067",
      "status": "Standard",
      "source": "pattern_generation"
    },
    {
      "id": 74,
      "nom": "FASHION DISTRICT FERRARA",
      "ville": "Ferrara",
      "region": "Italie",
      "adresse": "Centro storico, Ferrara, Italia",
      "type": "Multi-brand",
      "telephone": "+39 065 168 1068",
      "status": "Standard",
      "source": "pattern_generation"
    },
    {
      "id": 75,
      "nom": "STYLE HOUSE RIMINI",
      "ville": "Rimini",
      "region": "Italie",
      "adresse": "Centro storico, Rimini, Italia",
      "type": "Multi-brand",
      "telephone": "+39 076 169 1069",
      "status": "Standard",
      "source": "pattern_generation"
    },
    {
      "id": 76,
      "nom": "MODE BOUTIQUE SYRACUSE",
      "ville": "Syracuse",
      "region": "Italie",
      "adresse": "Centro storico, Syracuse, Italia",
      "type": "Multi-brand",
      "telephone": "+39 087 170 1070",
      "status": "Standard",
      "source": "pattern_generation"
    },
    {
      "id": 77,
      "nom": "FASHION CORNER SASSARI",
      "ville": "Sassari",
      "region": "Italie",
      "adresse": "Centro storico, Sassari, Italia",
      "type": "Multi-brand",
      "telephone": "+39 098 171 1071",
      "status": "Standard",
      "source": "pattern_generation"
    },
    {
      "id": 78,
      "nom": "LUXURY STORE MONZA",
      "ville": "Monza",
      "region": "Italie",
      "adresse": "Centro storico, Monza, Italia",
      "type": "Multi-brand",
      "telephone": "+39 011 172 1072",
      "status": "Standard",
      "source": "pattern_generation"
    },
    {
      "id": 79,
      "nom": "FASHION HUB BERGAMO",
      "ville": "Bergamo",
      "region": "Italie",
      "adresse": "Centro storico, Bergamo, Italia",
      "type": "Multi-brand",
      "telephone": "+39 022 173 1073",
      "status": "Standard",
      "source": "pattern_generation"
    },
    {
      "id": 80,
      "nom": "STYLE GALLERY FORLÌ",
      "ville": "Forlì",
      "region": "Italie",
      "adresse": "Centro storico, Forlì, Italia",
      "type": "Multi-brand",
      "telephone": "+39 033 174 1074",
      "status": "Standard",
      "source": "pattern_generation"
    },
    {
      "id": 81,
      "nom": "MODE CENTER TRENTO",
      "ville": "Trento",
      "region": "Italie",
      "adresse": "Centro storico, Trento, Italia",
      "type": "Multi-brand",
      "telephone": "+39 044 175 1075",
      "status": "Standard",
      "source": "pattern_generation"
    },
    {
      "id": 82,
      "nom": "PREMIUM STORE VICENZA",
      "ville": "Vicenza",
      "region": "Italie",
      "adresse": "Centro storico, Vicenza, Italia",
      "type": "Multi-brand",
      "telephone": "+39 055 176 1076",
      "status": "Standard",
      "source": "pattern_generation"
    },
    {
      "id": 83,
      "nom": "DESIGNER BOUTIQUE TERNI",
      "ville": "Terni",
      "region": "Italie",
      "adresse": "Centro storico, Terni, Italia",
      "type": "Multi-brand",
      "telephone": "+39 066 177 1077",
      "status": "Standard",
      "source": "pattern_generation"
    },
    {
      "id": 84,
      "nom": "FASHION POINT BOLZANO",
      "ville": "Bolzano",
      "region": "Italie",
      "adresse": "Centro storico, Bolzano, Italia",
      "type": "Multi-brand",
      "telephone": "+39 077 178 1078",
      "status": "Standard",
      "source": "pattern_generation"
    },
    {
      "id": 85,
      "nom": "STYLE STUDIO NOVARA",
      "ville": "Novara",
      "region": "Italie",
      "adresse": "Centro storico, Novara, Italia",
      "type": "Multi-brand",
      "telephone": "+39 088 179 1079",
      "status": "Standard",
      "source": "pattern_generation"
    },
    {
      "id": 86,
      "nom": "FASHION STORE PIACENZA",
      "ville": "Piacenza",
      "region": "Italie",
      "adresse": "Centro storico, Piacenza, Italia",
      "type": "Multi-brand",
      "telephone": "+39 091 180 1080",
      "status": "Standard",
      "source": "pattern_generation"
    },
    {
      "id": 87,
      "nom": "LUXURY BOUTIQUE ANCONA",
      "ville": "Ancona",
      "region": "Italie",
      "adresse": "Centro storico, Ancona, Italia",
      "type": "Multi-brand",
      "telephone": "+39 012 181 1081",
      "status": "Standard",
      "source": "pattern_generation"
    },
    {
      "id": 88,
      "nom": "MODE HOUSE AREZZO",
      "ville": "Arezzo",
      "region": "Italie",
      "adresse": "Centro storico, Arezzo, Italia",
      "type": "Multi-brand",
      "telephone": "+39 023 182 1082",
      "status": "Standard",
      "source": "pattern_generation"
    },
    {
      "id": 89,
      "nom": "STYLE CENTER UDINE",
      "ville": "Udine",
      "region": "Italie",
      "adresse": "Centro storico, Udine, Italia",
      "type": "Multi-brand",
      "telephone": "+39 034 183 1083",
      "status": "Standard",
      "source": "pattern_generation"
    },
    {
      "id": 90,
      "nom": "CONCEPT STORE CESENA",
      "ville": "Cesena",
      "region": "Italie",
      "adresse": "Centro storico, Cesena, Italia",
      "type": "Multi-brand",
      "telephone": "+39 045 184 1084",
      "status": "Standard",
      "source": "pattern_generation"
    },
    {
      "id": 91,
      "nom": "MULTI BRAND LECCE",
      "ville": "Lecce",
      "region": "Italie",
      "adresse": "Centro storico, Lecce, Italia",
      "type": "Multi-brand",
      "telephone": "+39 056 185 1085",
      "status": "Standard",
      "source": "pattern_generation"
    },
    {
      "id": 92,
      "nom": "FASHION GALLERY LA SPEZIA",
      "ville": "La Spezia",
      "region": "Italie",
      "adresse": "Centro storico, La Spezia, Italia",
      "type": "Multi-brand",
      "telephone": "+39 067 186 1086",
      "status": "Standard",
      "source": "pattern_generation"
    },
    {
      "id": 93,
      "nom": "BOUTIQUE ELEGANTE BRINDISI",
      "ville": "Brindisi",
      "region": "Italie",
      "adresse": "Centro storico, Brindisi, Italia",
      "type": "Multi-brand",
      "telephone": "+39 078 187 1087",
      "status": "Standard",
      "source": "pattern_generation"
    },
    {
      "id": 94,
      "nom": "FASHION DISTRICT MILANO",
      "ville": "Milano",
      "region": "Italie",
      "adresse": "Centro storico, Milano, Italia",
      "type": "Multi-brand",
      "telephone": "+39 081 188 1088",
      "status": "Standard",
      "source": "pattern_generation"
    },
    {
      "id": 95,
      "nom": "STYLE HOUSE ROMA",
      "ville": "Roma",
      "region": "Italie",
      "adresse": "Centro storico, Roma, Italia",
      "type": "Multi-brand",
      "telephone": "+39 092 189 1089",
      "status": "Standard",
      "source": "pattern_generation"
    },
    {
      "id": 96,
      "nom": "MODE BOUTIQUE FIRENZE",
      "ville": "Firenze",
      "region": "Italie",
      "adresse": "Centro storico, Firenze, Italia",
      "type": "Multi-brand",
      "telephone": "+39 013 190 1090",
      "status": "Standard",
      "source": "pattern_generation"
    },
    {
      "id": 97,
      "nom": "FASHION CORNER VENEZIA",
      "ville": "Venezia",
      "region": "Italie",
      "adresse": "Centro storico, Venezia, Italia",
      "type": "Multi-brand",
      "telephone": "+39 024 191 1091",
      "status": "Standard",
      "source": "pattern_generation"
    },
    {
      "id": 98,
      "nom": "LUXURY STORE NAPOLI",
      "ville": "Napoli",
      "region": "Italie",
      "adresse": "Centro storico, Napoli, Italia",
      "type": "Multi-brand",
      "telephone": "+39 035 192 1092",
      "status": "Standard",
      "source": "pattern_generation"
    },
    {
      "id": 99,
      "nom": "FASHION HUB BOLOGNA",
      "ville": "Bologna",
      "region": "Italie",
      "adresse": "Centro storico, Bologna, Italia",
      "type": "Multi-brand",
      "telephone": "+39 046 193 1093",
      "status": "Standard",
      "source": "pattern_generation"
    },
    {
      "id": 100,
      "nom": "STYLE GALLERY TORINO",
      "ville": "Torino",
      "region": "Italie",
      "adresse": "Centro storico, Torino, Italia",
      "type": "Multi-brand",
      "telephone": "+39 057 194 1094",
      "status": "Standard",
      "source": "pattern_generation"
    },
    {
      "id": 101,
      "nom": "MODE CENTER PALERMO",
      "ville": "Palermo",
      "region": "Italie",
      "adresse": "Centro storico, Palermo, Italia",
      "type": "Multi-brand",
      "telephone": "+39 068 195 1095",
      "status": "Standard",
      "source": "pattern_generation"
    },
    {
      "id": 102,
      "nom": "PREMIUM STORE GENOVA",
      "ville": "Genova",
      "region": "Italie",
      "adresse": "Centro storico, Genova, Italia",
      "type": "Multi-brand",
      "telephone": "+39 071 196 1096",
      "status": "Standard",
      "source": "pattern_generation"
    },
    {
      "id": 103,
      "nom": "DESIGNER BOUTIQUE VERONA",
      "ville": "Verona",
      "region": "Italie",
      "adresse": "Centro storico, Verona, Italia",
      "type": "Multi-brand",
      "telephone": "+39 082 197 1097",
      "status": "Standard",
      "source": "pattern_generation"
    },
    {
      "id": 104,
      "nom": "FASHION POINT BARI",
      "ville": "Bari",
      "region": "Italie",
      "adresse": "Centro storico, Bari, Italia",
      "type": "Multi-brand",
      "telephone": "+39 093 198 1098",
      "status": "Standard",
      "source": "pattern_generation"
    },
    {
      "id": 105,
      "nom": "STYLE STUDIO CATANIA",
      "ville": "Catania",
      "region": "Italie",
      "adresse": "Centro storico, Catania, Italia",
      "type": "Multi-brand",
      "telephone": "+39 014 199 1099",
      "status": "Standard",
      "source": "pattern_generation"
    },
    {
      "id": 106,
      "nom": "FASHION STORE PADOVA",
      "ville": "Padova",
      "region": "Italie",
      "adresse": "Centro storico, Padova, Italia",
      "type": "Multi-brand",
      "telephone": "+39 025 200 1100",
      "status": "Standard",
      "source": "pattern_generation"
    },
    {
      "id": 107,
      "nom": "LUXURY BOUTIQUE TRIESTE",
      "ville": "Trieste",
      "region": "Italie",
      "adresse": "Centro storico, Trieste, Italia",
      "type": "Multi-brand",
      "telephone": "+39 036 201 1101",
      "status": "Standard",
      "source": "pattern_generation"
    },
    {
      "id": 108,
      "nom": "MODE HOUSE BRESCIA",
      "ville": "Brescia",
      "region": "Italie",
      "adresse": "Centro storico, Brescia, Italia",
      "type": "Multi-brand",
      "telephone": "+39 047 202 1102",
      "status": "Standard",
      "source": "pattern_generation"
    },
    {
      "id": 109,
      "nom": "STYLE CENTER PARMA",
      "ville": "Parma",
      "region": "Italie",
      "adresse": "Centro storico, Parma, Italia",
      "type": "Multi-brand",
      "telephone": "+39 058 203 1103",
      "status": "Standard",
      "source": "pattern_generation"
    },
    {
      "id": 110,
      "nom": "CONCEPT STORE MODENA",
      "ville": "Modena",
      "region": "Italie",
      "adresse": "Centro storico, Modena, Italia",
      "type": "Multi-brand",
      "telephone": "+39 061 204 1104",
      "status": "Standard",
      "source": "pattern_generation"
    },
    {
      "id": 111,
      "nom": "MULTI BRAND REGGIO EMILIA",
      "ville": "Reggio Emilia",
      "region": "Italie",
      "adresse": "Centro storico, Reggio Emilia, Italia",
      "type": "Multi-brand",
      "telephone": "+39 072 205 1105",
      "status": "Standard",
      "source": "pattern_generation"
    },
    {
      "id": 112,
      "nom": "FASHION GALLERY PERUGIA",
      "ville": "Perugia",
      "region": "Italie",
      "adresse": "Centro storico, Perugia, Italia",
      "type": "Multi-brand",
      "telephone": "+39 083 206 1106",
      "status": "Standard",
      "source": "pattern_generation"
    },
    {
      "id": 113,
      "nom": "BOUTIQUE ELEGANTE RAVENNA",
      "ville": "Ravenna",
      "region": "Italie",
      "adresse": "Centro storico, Ravenna, Italia",
      "type": "Multi-brand",
      "telephone": "+39 094 207 1107",
      "status": "Standard",
      "source": "pattern_generation"
    },
    {
      "id": 114,
      "nom": "FASHION DISTRICT LIVORNO",
      "ville": "Livorno",
      "region": "Italie",
      "adresse": "Centro storico, Livorno, Italia",
      "type": "Multi-brand",
      "telephone": "+39 015 208 1108",
      "status": "Standard",
      "source": "pattern_generation"
    },
    {
      "id": 115,
      "nom": "STYLE HOUSE CAGLIARI",
      "ville": "Cagliari",
      "region": "Italie",
      "adresse": "Centro storico, Cagliari, Italia",
      "type": "Multi-brand",
      "telephone": "+39 026 209 1109",
      "status": "Standard",
      "source": "pattern_generation"
    },
    {
      "id": 116,
      "nom": "MODE BOUTIQUE FOGGIA",
      "ville": "Foggia",
      "region": "Italie",
      "adresse": "Centro storico, Foggia, Italia",
      "type": "Multi-brand",
      "telephone": "+39 037 210 1110",
      "status": "Standard",
      "source": "pattern_generation"
    },
    {
      "id": 117,
      "nom": "FASHION CORNER SALERNO",
      "ville": "Salerno",
      "region": "Italie",
      "adresse": "Centro storico, Salerno, Italia",
      "type": "Multi-brand",
      "telephone": "+39 048 211 1111",
      "status": "Standard",
      "source": "pattern_generation"
    },
    {
      "id": 118,
      "nom": "LUXURY STORE FERRARA",
      "ville": "Ferrara",
      "region": "Italie",
      "adresse": "Centro storico, Ferrara, Italia",
      "type": "Multi-brand",
      "telephone": "+39 051 212 1112",
      "status": "Standard",
      "source": "pattern_generation"
    },
    {
      "id": 119,
      "nom": "FASHION HUB RIMINI",
      "ville": "Rimini",
      "region": "Italie",
      "adresse": "Centro storico, Rimini, Italia",
      "type": "Multi-brand",
      "telephone": "+39 062 213 1113",
      "status": "Standard",
      "source": "pattern_generation"
    },
    {
      "id": 120,
      "nom": "STYLE GALLERY SYRACUSE",
      "ville": "Syracuse",
      "region": "Italie",
      "adresse": "Centro storico, Syracuse, Italia",
      "type": "Multi-brand",
      "telephone": "+39 073 214 1114",
      "status": "Standard",
      "source": "pattern_generation"
    },
    {
      "id": 121,
      "nom": "MODE CENTER SASSARI",
      "ville": "Sassari",
      "region": "Italie",
      "adresse": "Centro storico, Sassari, Italia",
      "type": "Multi-brand",
      "telephone": "+39 084 215 1115",
      "status": "Standard",
      "source": "pattern_generation"
    },
    {
      "id": 122,
      "nom": "PREMIUM STORE MONZA",
      "ville": "Monza",
      "region": "Italie",
      "adresse": "Centro storico, Monza, Italia",
      "type": "Multi-brand",
      "telephone": "+39 095 216 1116",
      "status": "Standard",
      "source": "pattern_generation"
    },
    {
      "id": 123,
      "nom": "DESIGNER BOUTIQUE BERGAMO",
      "ville": "Bergamo",
      "region": "Italie",
      "adresse": "Centro storico, Bergamo, Italia",
      "type": "Multi-brand",
      "telephone": "+39 016 217 1117",
      "status": "Standard",
      "source": "pattern_generation"
    },
    {
      "id": 124,
      "nom": "FASHION POINT FORLÌ",
      "ville": "Forlì",
      "region": "Italie",
      "adresse": "Centro storico, Forlì, Italia",
      "type": "Multi-brand",
      "telephone": "+39 027 218 1118",
      "status": "Standard",
      "source": "pattern_generation"
    },
    {
      "id": 125,
      "nom": "STYLE STUDIO TRENTO",
      "ville": "Trento",
      "region": "Italie",
      "adresse": "Centro storico, Trento, Italia",
      "type": "Multi-brand",
      "telephone": "+39 038 219 1119",
      "status": "Standard",
      "source": "pattern_generation"
    },
    {
      "id": 126,
      "nom": "FASHION STORE VICENZA",
      "ville": "Vicenza",
      "region": "Italie",
      "adresse": "Centro storico, Vicenza, Italia",
      "type": "Multi-brand",
      "telephone": "+39 041 220 1120",
      "status": "Standard",
      "source": "pattern_generation"
    },
    {
      "id": 127,
      "nom": "LUXURY BOUTIQUE TERNI",
      "ville": "Terni",
      "region": "Italie",
      "adresse": "Centro storico, Terni, Italia",
      "type": "Multi-brand",
      "telephone": "+39 052 221 1121",
      "status": "Standard",
      "source": "pattern_generation"
    },
    {
      "id": 128,
      "nom": "MODE HOUSE BOLZANO",
      "ville": "Bolzano",
      "region": "Italie",
      "adresse": "Centro storico, Bolzano, Italia",
      "type": "Multi-brand",
      "telephone": "+39 063 222 1122",
      "status": "Standard",
      "source": "pattern_generation"
    },
    {
      "id": 129,
      "nom": "STYLE CENTER NOVARA",
      "ville": "Novara",
      "region": "Italie",
      "adresse": "Centro storico, Novara, Italia",
      "type": "Multi-brand",
      "telephone": "+39 074 223 1123",
      "status": "Standard",
      "source": "pattern_generation"
    },
    {
      "id": 130,
      "nom": "CONCEPT STORE PIACENZA",
      "ville": "Piacenza",
      "region": "Italie",
      "adresse": "Centro storico, Piacenza, Italia",
      "type": "Multi-brand",
      "telephone": "+39 085 224 1124",
      "status": "Standard",
      "source": "pattern_generation"
    },
    {
      "id": 131,
      "nom": "MULTI BRAND ANCONA",
      "ville": "Ancona",
      "region": "Italie",
      "adresse": "Centro storico, Ancona, Italia",
      "type": "Multi-brand",
      "telephone": "+39 096 225 1125",
      "status": "Standard",
      "source": "pattern_generation"
    },
    {
      "id": 132,
      "nom": "FASHION GALLERY AREZZO",
      "ville": "Arezzo",
      "region": "Italie",
      "adresse": "Centro storico, Arezzo, Italia",
      "type": "Multi-brand",
      "telephone": "+39 017 226 1126",
      "status": "Standard",
      "source": "pattern_generation"
    },
    {
      "id": 133,
      "nom": "BOUTIQUE ELEGANTE UDINE",
      "ville": "Udine",
      "region": "Italie",
      "adresse": "Centro storico, Udine, Italia",
      "type": "Multi-brand",
      "telephone": "+39 028 227 1127",
      "status": "Standard",
      "source": "pattern_generation"
    },
    {
      "id": 134,
      "nom": "FASHION DISTRICT CESENA",
      "ville": "Cesena",
      "region": "Italie",
      "adresse": "Centro storico, Cesena, Italia",
      "type": "Multi-brand",
      "telephone": "+39 031 228 1128",
      "status": "Standard",
      "source": "pattern_generation"
    },
    {
      "id": 135,
      "nom": "STYLE HOUSE LECCE",
      "ville": "Lecce",
      "region": "Italie",
      "adresse": "Centro storico, Lecce, Italia",
      "type": "Multi-brand",
      "telephone": "+39 042 229 1129",
      "status": "Standard",
      "source": "pattern_generation"
    },
    {
      "id": 136,
      "nom": "MODE BOUTIQUE LA SPEZIA",
      "ville": "La Spezia",
      "region": "Italie",
      "adresse": "Centro storico, La Spezia, Italia",
      "type": "Multi-brand",
      "telephone": "+39 053 230 1130",
      "status": "Standard",
      "source": "pattern_generation"
    },
    {
      "id": 137,
      "nom": "FASHION CORNER BRINDISI",
      "ville": "Brindisi",
      "region": "Italie",
      "adresse": "Centro storico, Brindisi, Italia",
      "type": "Multi-brand",
      "telephone": "+39 064 231 1131",
      "status": "Standard",
      "source": "pattern_generation"
    },
    {
      "id": 138,
      "nom": "LUXURY STORE MILANO",
      "ville": "Milano",
      "region": "Italie",
      "adresse": "Centro storico, Milano, Italia",
      "type": "Multi-brand",
      "telephone": "+39 075 232 1132",
      "status": "Standard",
      "source": "pattern_generation"
    },
    {
      "id": 139,
      "nom": "FASHION HUB ROMA",
      "ville": "Roma",
      "region": "Italie",
      "adresse": "Centro storico, Roma, Italia",
      "type": "Multi-brand",
      "telephone": "+39 086 233 1133",
      "status": "Standard",
      "source": "pattern_generation"
    },
    {
      "id": 140,
      "nom": "STYLE GALLERY FIRENZE",
      "ville": "Firenze",
      "region": "Italie",
      "adresse": "Centro storico, Firenze, Italia",
      "type": "Multi-brand",
      "telephone": "+39 097 234 1134",
      "status": "Standard",
      "source": "pattern_generation"
    },
    {
      "id": 141,
      "nom": "MODE CENTER VENEZIA",
      "ville": "Venezia",
      "region": "Italie",
      "adresse": "Centro storico, Venezia, Italia",
      "type": "Multi-brand",
      "telephone": "+39 018 235 1135",
      "status": "Standard",
      "source": "pattern_generation"
    },
    {
      "id": 142,
      "nom": "PREMIUM STORE NAPOLI",
      "ville": "Napoli",
      "region": "Italie",
      "adresse": "Centro storico, Napoli, Italia",
      "type": "Multi-brand",
      "telephone": "+39 021 236 1136",
      "status": "Standard",
      "source": "pattern_generation"
    },
    {
      "id": 143,
      "nom": "DESIGNER BOUTIQUE BOLOGNA",
      "ville": "Bologna",
      "region": "Italie",
      "adresse": "Centro storico, Bologna, Italia",
      "type": "Multi-brand",
      "telephone": "+39 032 237 1137",
      "status": "Standard",
      "source": "pattern_generation"
    },
    {
      "id": 144,
      "nom": "FASHION POINT TORINO",
      "ville": "Torino",
      "region": "Italie",
      "adresse": "Centro storico, Torino, Italia",
      "type": "Multi-brand",
      "telephone": "+39 043 238 1138",
      "status": "Standard",
      "source": "pattern_generation"
    },
    {
      "id": 145,
      "nom": "STYLE STUDIO PALERMO",
      "ville": "Palermo",
      "region": "Italie",
      "adresse": "Centro storico, Palermo, Italia",
      "type": "Multi-brand",
      "telephone": "+39 054 239 1139",
      "status": "Standard",
      "source": "pattern_generation"
    },
    {
      "id": 146,
      "nom": "FASHION STORE GENOVA",
      "ville": "Genova",
      "region": "Italie",
      "adresse": "Centro storico, Genova, Italia",
      "type": "Multi-brand",
      "telephone": "+39 065 240 1140",
      "status": "Standard",
      "source": "pattern_generation"
    },
    {
      "id": 147,
      "nom": "LUXURY BOUTIQUE VERONA",
      "ville": "Verona",
      "region": "Italie",
      "adresse": "Centro storico, Verona, Italia",
      "type": "Multi-brand",
      "telephone": "+39 076 241 1141",
      "status": "Standard",
      "source": "pattern_generation"
    },
    {
      "id": 148,
      "nom": "MODE HOUSE BARI",
      "ville": "Bari",
      "region": "Italie",
      "adresse": "Centro storico, Bari, Italia",
      "type": "Multi-brand",
      "telephone": "+39 087 242 1142",
      "status": "Standard",
      "source": "pattern_generation"
    },
    {
      "id": 149,
      "nom": "STYLE CENTER CATANIA",
      "ville": "Catania",
      "region": "Italie",
      "adresse": "Centro storico, Catania, Italia",
      "type": "Multi-brand",
      "telephone": "+39 098 243 1143",
      "status": "Standard",
      "source": "pattern_generation"
    },
    {
      "id": 150,
      "nom": "CONCEPT STORE PADOVA",
      "ville": "Padova",
      "region": "Italie",
      "adresse": "Centro storico, Padova, Italia",
      "type": "Multi-brand",
      "telephone": "+39 011 244 1144",
      "status": "Standard",
      "source": "pattern_generation"
    },
    {
      "id": 151,
      "nom": "MULTI BRAND TRIESTE",
      "ville": "Trieste",
      "region": "Italie",
      "adresse": "Centro storico, Trieste, Italia",
      "type": "Multi-brand",
      "telephone": "+39 022 245 1145",
      "status": "Standard",
      "source": "pattern_generation"
    },
    {
      "id": 152,
      "nom": "FASHION GALLERY BRESCIA",
      "ville": "Brescia",
      "region": "Italie",
      "adresse": "Centro storico, Brescia, Italia",
      "type": "Multi-brand",
      "telephone": "+39 033 246 1146",
      "status": "Standard",
      "source": "pattern_generation"
    },
    {
      "id": 153,
      "nom": "BOUTIQUE ELEGANTE PARMA",
      "ville": "Parma",
      "region": "Italie",
      "adresse": "Centro storico, Parma, Italia",
      "type": "Multi-brand",
      "telephone": "+39 044 247 1147",
      "status": "Standard",
      "source": "pattern_generation"
    },
    {
      "id": 154,
      "nom": "FASHION DISTRICT MODENA",
      "ville": "Modena",
      "region": "Italie",
      "adresse": "Centro storico, Modena, Italia",
      "type": "Multi-brand",
      "telephone": "+39 055 248 1148",
      "status": "Standard",
      "source": "pattern_generation"
    },
    {
      "id": 155,
      "nom": "STYLE HOUSE REGGIO EMILIA",
      "ville": "Reggio Emilia",
      "region": "Italie",
      "adresse": "Centro storico, Reggio Emilia, Italia",
      "type": "Multi-brand",
      "telephone": "+39 066 249 1149",
      "status": "Standard",
      "source": "pattern_generation"
    },
    {
      "id": 156,
      "nom": "MODE BOUTIQUE PERUGIA",
      "ville": "Perugia",
      "region": "Italie",
      "adresse": "Centro storico, Perugia, Italia",
      "type": "Multi-brand",
      "telephone": "+39 077 250 1150",
      "status": "Standard",
      "source": "pattern_generation"
    },
    {
      "id": 157,
      "nom": "FASHION CORNER RAVENNA",
      "ville": "Ravenna",
      "region": "Italie",
      "adresse": "Centro storico, Ravenna, Italia",
      "type": "Multi-brand",
      "telephone": "+39 088 251 1151",
      "status": "Standard",
      "source": "pattern_generation"
    },
    {
      "id": 158,
      "nom": "LUXURY STORE LIVORNO",
      "ville": "Livorno",
      "region": "Italie",
      "adresse": "Centro storico, Livorno, Italia",
      "type": "Multi-brand",
      "telephone": "+39 091 252 1152",
      "status": "Standard",
      "source": "pattern_generation"
    },
    {
      "id": 159,
      "nom": "FASHION HUB CAGLIARI",
      "ville": "Cagliari",
      "region": "Italie",
      "adresse": "Centro storico, Cagliari, Italia",
      "type": "Multi-brand",
      "telephone": "+39 012 253 1153",
      "status": "Standard",
      "source": "pattern_generation"
    },
    {
      "id": 160,
      "nom": "STYLE GALLERY FOGGIA",
      "ville": "Foggia",
      "region": "Italie",
      "adresse": "Centro storico, Foggia, Italia",
      "type": "Multi-brand",
      "telephone": "+39 023 254 1154",
      "status": "Standard",
      "source": "pattern_generation"
    },
    {
      "id": 161,
      "nom": "MODE CENTER SALERNO",
      "ville": "Salerno",
      "region": "Italie",
      "adresse": "Centro storico, Salerno, Italia",
      "type": "Multi-brand",
      "telephone": "+39 034 255 1155",
      "status": "Standard",
      "source": "pattern_generation"
    },
    {
      "id": 162,
      "nom": "PREMIUM STORE FERRARA",
      "ville": "Ferrara",
      "region": "Italie",
      "adresse": "Centro storico, Ferrara, Italia",
      "type": "Multi-brand",
      "telephone": "+39 045 256 1156",
      "status": "Standard",
      "source": "pattern_generation"
    },
    {
      "id": 163,
      "nom": "DESIGNER BOUTIQUE RIMINI",
      "ville": "Rimini",
      "region": "Italie",
      "adresse": "Centro storico, Rimini, Italia",
      "type": "Multi-brand",
      "telephone": "+39 056 257 1157",
      "status": "Standard",
      "source": "pattern_generation"
    },
    {
      "id": 164,
      "nom": "FASHION POINT SYRACUSE",
      "ville": "Syracuse",
      "region": "Italie",
      "adresse": "Centro storico, Syracuse, Italia",
      "type": "Multi-brand",
      "telephone": "+39 067 258 1158",
      "status": "Standard",
      "source": "pattern_generation"
    },
    {
      "id": 165,
      "nom": "STYLE STUDIO SASSARI",
      "ville": "Sassari",
      "region": "Italie",
      "adresse": "Centro storico, Sassari, Italia",
      "type": "Multi-brand",
      "telephone": "+39 078 259 1159",
      "status": "Standard",
      "source": "pattern_generation"
    },
    {
      "id": 166,
      "nom": "FASHION STORE MONZA",
      "ville": "Monza",
      "region": "Italie",
      "adresse": "Centro storico, Monza, Italia",
      "type": "Multi-brand",
      "telephone": "+39 081 260 1160",
      "status": "Standard",
      "source": "pattern_generation"
    },
    {
      "id": 167,
      "nom": "LUXURY BOUTIQUE BERGAMO",
      "ville": "Bergamo",
      "region": "Italie",
      "adresse": "Centro storico, Bergamo, Italia",
      "type": "Multi-brand",
      "telephone": "+39 092 261 1161",
      "status": "Standard",
      "source": "pattern_generation"
    },
    {
      "id": 168,
      "nom": "MODE HOUSE FORLÌ",
      "ville": "Forlì",
      "region": "Italie",
      "adresse": "Centro storico, Forlì, Italia",
      "type": "Multi-brand",
      "telephone": "+39 013 262 1162",
      "status": "Standard",
      "source": "pattern_generation"
    },
    {
      "id": 169,
      "nom": "STYLE CENTER TRENTO",
      "ville": "Trento",
      "region": "Italie",
      "adresse": "Centro storico, Trento, Italia",
      "type": "Multi-brand",
      "telephone": "+39 024 263 1163",
      "status": "Standard",
      "source": "pattern_generation"
    },
    {
      "id": 170,
      "nom": "CONCEPT STORE VICENZA",
      "ville": "Vicenza",
      "region": "Italie",
      "adresse": "Centro storico, Vicenza, Italia",
      "type": "Multi-brand",
      "telephone": "+39 035 264 1164",
      "status": "Standard",
      "source": "pattern_generation"
    },
    {
      "id": 171,
      "nom": "MULTI BRAND TERNI",
      "ville": "Terni",
      "region": "Italie",
      "adresse": "Centro storico, Terni, Italia",
      "type": "Multi-brand",
      "telephone": "+39 046 265 1165",
      "status": "Standard",
      "source": "pattern_generation"
    },
    {
      "id": 172,
      "nom": "FASHION GALLERY BOLZANO",
      "ville": "Bolzano",
      "region": "Italie",
      "adresse": "Centro storico, Bolzano, Italia",
      "type": "Multi-brand",
      "telephone": "+39 057 266 1166",
      "status": "Standard",
      "source": "pattern_generation"
    },
    {
      "id": 173,
      "nom": "BOUTIQUE ELEGANTE NOVARA",
      "ville": "Novara",
      "region": "Italie",
      "adresse": "Centro storico, Novara, Italia",
      "type": "Multi-brand",
      "telephone": "+39 068 267 1167",
      "status": "Standard",
      "source": "pattern_generation"
    },
    {
      "id": 174,
      "nom": "FASHION DISTRICT PIACENZA",
      "ville": "Piacenza",
      "region": "Italie",
      "adresse": "Centro storico, Piacenza, Italia",
      "type": "Multi-brand",
      "telephone": "+39 071 268 1168",
      "status": "Standard",
      "source": "pattern_generation"
    },
    {
      "id": 175,
      "nom": "STYLE HOUSE ANCONA",
      "ville": "Ancona",
      "region": "Italie",
      "adresse": "Centro storico, Ancona, Italia",
      "type": "Multi-brand",
      "telephone": "+39 082 269 1169",
      "status": "Standard",
      "source": "pattern_generation"
    },
    {
      "id": 176,
      "nom": "MODE BOUTIQUE AREZZO",
      "ville": "Arezzo",
      "region": "Italie",
      "adresse": "Centro storico, Arezzo, Italia",
      "type": "Multi-brand",
      "telephone": "+39 093 270 1170",
      "status": "Standard",
      "source": "pattern_generation"
    },
    {
      "id": 177,
      "nom": "FASHION CORNER UDINE",
      "ville": "Udine",
      "region": "Italie",
      "adresse": "Centro storico, Udine, Italia",
      "type": "Multi-brand",
      "telephone": "+39 014 271 1171",
      "status": "Standard",
      "source": "pattern_generation"
    },
    {
      "id": 178,
      "nom": "LUXURY STORE CESENA",
      "ville": "Cesena",
      "region": "Italie",
      "adresse": "Centro storico, Cesena, Italia",
      "type": "Multi-brand",
      "telephone": "+39 025 272 1172",
      "status": "Standard",
      "source": "pattern_generation"
    },
    {
      "id": 179,
      "nom": "FASHION HUB LECCE",
      "ville": "Lecce",
      "region": "Italie",
      "adresse": "Centro storico, Lecce, Italia",
      "type": "Multi-brand",
      "telephone": "+39 036 273 1173",
      "status": "Standard",
      "source": "pattern_generation"
    },
    {
      "id": 180,
      "nom": "STYLE GALLERY LA SPEZIA",
      "ville": "La Spezia",
      "region": "Italie",
      "adresse": "Centro storico, La Spezia, Italia",
      "type": "Multi-brand",
      "telephone": "+39 047 274 1174",
      "status": "Standard",
      "source": "pattern_generation"
    }
  ]
}